innertubei/__init__.py
innertubei/__version__.py
innertubei/extras.py
innertubei/search.py
innertubei/core/__init__.py
innertubei/core/channel.py
innertubei/core/channelsearch.py
innertubei/core/componenthandler.py
innertubei/core/constants.py
innertubei/core/hashtag.py
innertubei/core/playlist.py
innertubei/core/requests.py
innertubei/core/search.py
innertubei/core/suggestions.py
innertubei/core/transcript.py
innertubei/core/video.py
innertubei/handlers/__init__.py
innertubei/handlers/componenthandler.py
innertubei/handlers/requesthandler.py
innertubei-0.5.2.dist-info/METADATA
innertubei-0.5.2.dist-info/WHEEL
innertubei-0.5.2.dist-info/licenses/LICENSE
innertubei-0.5.2.dist-info/RECORD
